pysentimentanalyzer/__init__.py
pysentimentanalyzer/generate_wordcloud.py
pysentimentanalyzer/get_aggregated_sentiment_score.py
pysentimentanalyzer/helper.py
pysentimentanalyzer/likert_scale.py
pysentimentanalyzer/sentiment_score_plot.py
pysentimentanalyzer-1.0.0.dist-info/METADATA
pysentimentanalyzer-1.0.0.dist-info/WHEEL
pysentimentanalyzer-1.0.0.dist-info/LICENSE
pysentimentanalyzer-1.0.0.dist-info/RECORD
